Metadata-Version: 2.1
Name: odoo13-addon-l10n-es-aeat-mod390-oss
Version: 13.0.1.0.1.dev3
Summary: AEAT modelo 390 - OSS
Home-page: https://github.com/OCA/l10n-spain
Author: Sygel, Odoo Community Association (OCA)
Author-email: support@odoo-community.org
License: AGPL-3
Platform: UNKNOWN
Classifier: Programming Language :: Python
Classifier: Framework :: Odoo
Classifier: Framework :: Odoo :: 13.0
Classifier: License :: OSI Approved :: GNU Affero General Public License v3
Requires-Python: >=3.5
Requires-Dist: odoo13-addon-l10n-es-aeat-mod390
Requires-Dist: odoo13-addon-l10n-eu-oss
Requires-Dist: odoo <13.1dev,>=13.0a
